utf12/__init__.py
utf12/utf12.py
utf12-1.0.0.dist-info/METADATA
utf12-1.0.0.dist-info/WHEEL
utf12-1.0.0.dist-info/licenses/LICENSE
utf12-1.0.0.dist-info/RECORD
