Metadata-Version: 2.3
Name: utf12
Version: 1.0.0
Summary: UTF-12 encoder
Project-URL: Homepage, https://github.com/lukejbullard/utf-12
Project-URL: Issues, https://github.com/lukejbullard/utf-12/issues
Author-email: Luke Bullard <2201010+LukeJBullard@users.noreply.github.com>
License-File: LICENSE
Classifier: License :: OSI Approved :: MIT License
Classifier: Operating System :: OS Independent
Classifier: Programming Language :: Python :: 3
Requires-Python: >=3.8
Requires-Dist: bitstring
